Metadata-Version: 2.1
Name: jupyter-kernel-gateway
Version: 3.0.0
Summary: A web server for spawning and communicating with Jupyter kernels
Project-URL: Homepage, http://github.com/jupyter-incubator/kernel_gateway
Author-email: Jupyter Development Team <jupyter@googlegroups.com>
License: # Licensing terms
License-File: LICENSE.md
Keywords: Cloud,Interactive,Interpreter,Kernel,Web
Classifier: Intended Audience :: Developers
Classifier: Intended Audience :: Science/Research
Classifier: Intended Audience :: System Administrators
Classifier: License :: OSI Approved :: BSD License
Classifier: Operating System :: OS Independent
Classifier: Programming Language :: Python
Classifier: Programming Language :: Python :: 3
Classifier: Programming Language :: Python :: 3.8
Classifier: Programming Language :: Python :: 3.9
Classifier: Programming Language :: Python :: 3.10
Classifier: Programming Language :: Python :: 3.11
Requires-Python: >=3.8
Requires-Dist: jupyter-client>=8.6
Requires-Dist: jupyter-core>=5.7
Requires-Dist: jupyter-server>=2.12
Requires-Dist: requests>=2.31
Requires-Dist: tornado>=6.4
Requires-Dist: traitlets>=5.14.1
Provides-Extra: docs
Requires-Dist: myst-parser; extra == 'docs'
Requires-Dist: sphinx; extra == 'docs'
Requires-Dist: sphinx-rtd-theme; extra == 'docs'
Provides-Extra: test
Requires-Dist: coverage; extra == 'test'
Requires-Dist: ipykernel; extra == 'test'
Requires-Dist: pytest; extra == 'test'
Requires-Dist: pytest-cov; extra == 'test'
Requires-Dist: pytest-jupyter; extra == 'test'
Requires-Dist: pytest-timeout; extra == 'test'
